termcolorx/__init__.py
termcolorx/animation.py
termcolorx/color.py
termcolorx/gradient.py
termcolorx/logger.py
termcolorx/platform.py
termcolorx-0.0.1.dist-info/METADATA
termcolorx-0.0.1.dist-info/WHEEL
termcolorx-0.0.1.dist-info/top_level.txt
termcolorx-0.0.1.dist-info/RECORD
