Metadata-Version: 2.4
Name: termcolorx
Version: 0.0.1
Summary: Library pewarna teks terminal lengkap (ANSI, RGB, Gradien, Logger, Animasi) dari dasar.
Home-page: https://github.com/Athallah1234/termcolorx
Author: ATHALLAH RAJENDRA PUTRA JUNIARTO
Author-email: athallahwork50@gmail.com
Classifier: Programming Language :: Python :: 3
Classifier: Topic :: Terminals
Classifier: Topic :: Utilities
Classifier: Operating System :: OS Independent
Requires-Python: >=3.13
Dynamic: author
Dynamic: author-email
Dynamic: classifier
Dynamic: description
Dynamic: description-content-type
Dynamic: home-page
Dynamic: requires-python
Dynamic: summary
